README.md
setup.cfg
setup.py
src/compydre/__init__.py
src/compydre/asnr_reader.py
src/compydre/comadre_reader.py
src/compydre/network_analysis.py
src/compydre.egg-info/PKG-INFO
src/compydre.egg-info/SOURCES.txt
src/compydre.egg-info/dependency_links.txt
src/compydre.egg-info/not-zip-safe
src/compydre.egg-info/requires.txt
src/compydre.egg-info/top_level.txt