Metadata-Version: 1.2
Name: compydre
Version: 0.0.1
Summary: Package for animal behavior network analysis
Home-page: https://github.com/lexalus/compydre
Author: Alexandra Beattie
Author-email: alexandra.k.beattie@ou.edu
License: UNKNOWN
Download-URL: https://github.com/lexalus/compydre/archive/0.0.1.tar.gz
Platform: UNKNOWN
Classifier: Intended Audience :: Developers
Classifier: License :: OSI Approved :: BSD License
Classifier: Operating System :: Unix
Classifier: Operating System :: POSIX
Classifier: Operating System :: Microsoft :: Windows
Classifier: Programming Language :: Python :: 3.8
Classifier: Programming Language :: Python :: 3.9
Classifier: Programming Language :: Python :: Implementation :: CPython
Classifier: Programming Language :: Python :: Implementation :: PyPy
Classifier: Topic :: Utilities
Requires-Python: >=3.6, !=3.0.*, !=3.1.*, !=3.2.*, !=3.3.*, !=3.4.*
